{
  "circulo_time1_dribles": 85,
  "circulo_time1_precisao_fin": 73,
  "circulo_time1_precisao_pas": 88,
  "circulo_time2_dribles": 89,
  "circulo_time2_precisao_fin": 90,
  "circulo_time2_precisao_pas": 84,
  "tabela_time1_posse_bola": "52",
  "tabela_time1_recuperacao_bola": "9",
  "tabela_time1_finalizacoes": "11",
  "tabela_time1_passes": "187",
  "tabela_time1_divididas": "16",
  "tabela_time1_divididas_ganhas": "10",
  "tabela_time1_interceptacoes": "21",
  "tabela_time1_defesas": "2",
  "tabela_time1_faltas_cometidas": "0",
  "tabela_time1_impedimentos": "2",
  "tabela_time1_escanteios": "3",
  "tabela_time1_faltas": "4",
  "tabela_time1_penaltis": "1",
  "tabela_time1_cartoes_amarelos": "0",
  "tabela_time2_posse_bola": "48",
  "tabela_time2_recuperacao_bola": "8",
  "tabela_time2_finalizacoes": "10",
  "tabela_time2_passes": "176",
  "tabela_time2_divididas": "43",
  "tabela_time2_divididas_ganhas": "18",
  "tabela_time2_interceptacoes": "16",
  "tabela_time2_defesas": "2",
  "tabela_time2_faltas_cometidas": "2",
  "tabela_time2_impedimentos": "3",
  "tabela_time2_escanteios": "2",
  "tabela_time2_faltas": "2",
  "tabela_time2_penaltis": "0",
  "tabela_time2_cartoes_amarelos": "1",
  "tabela_time1_gols_esperados": "5,3",
  "tabela_time2_gols_esperados": "5,7"
}